Metadata-Version: 1.1
Name: chattyraspi-script
Version: 0.0.1
Summary: Chattyraspi tool to run arbitrary command
Home-page: https://github.com/fcracker79/chattyraspi-script
Author: fcracker79
Author-email: fcracker79@gmail.com
License: MIT
Keywords: alexa smart-home
Platform: UNKNOWN
Classifier: Development Status :: 4 - Beta
Classifier: Intended Audience :: Developers
Classifier: Topic :: Software Development
Classifier: License :: OSI Approved :: MIT License
Classifier: Programming Language :: Python :: 3.2
Classifier: Programming Language :: Python :: 3.3
Classifier: Programming Language :: Python :: 3.4
Classifier: Programming Language :: Python :: 3.5
Classifier: Programming Language :: Python :: 3.6
Classifier: Programming Language :: Python :: 3.7
